{
    "pipeline_parameters": {
        "data_file": "data/smallville_846.csv",
        "feature_keys": [
            "text-embedding-3-small"
        ],
        "score_keys": [
            "mean"
        ],
        "target_gens": 50,
        "eval_random_states": [
            0,
            1,
            2,
            3
        ],
        "id": null
    },
    "tpot_parameters": {
        "search_space": {
            "node_type": "GraphSearchPipeline",
            "root_search_space": {
                "node_type": "EstimatorNode",
                "class_name": "regressors"
            },
            "inner_search_space": {
                "node_type": "ChoicePipeline",
                "search_spaces": [
                    {
                        "node_type": "EstimatorNode",
                        "class_name": "all_transformers"
                    },
                    {
                        "node_type": "EstimatorNode",
                        "class_name": "Passthrough"
                    }
                ]
            },
            "leaf_search_space": {
                "node_type": "ChoicePipeline",
                "search_spaces": [
                    {
                        "node_type": "EstimatorNode",
                        "class_name": "selectors_regression"
                    },
                    {
                        "node_type": "GeneticFeatureSelectorNode"
                    },
                    {
                        "node_type": "EstimatorNode",
                        "class_name": "Passthrough"
                    }
                ]
            }
        },
        "scorers": [
            "neg_mean_squared_error",
            "tpot.objectives.complexity_scorer"
        ],
        "scorers_weights": [
            1,
            -1
        ],
        "classification": false,
        "cv": 9,
        "bigger_is_better": true,
        "population_size": 100,
        "generations": 1,
        "max_time_mins": 220,
        "max_eval_time_mins": 10,
        "early_stop": 10,
        "scorers_early_stop_tol": 0.001,
        "other_objectives_early_stop_tol": null,
        "warm_start": true,
        "verbose": 4,
        "random_state": null
    }
}
